tmp_folder/__init__.py
tmp_folder/main.py
tmp_folder-0.2.0.dist-info/LICENSE
tmp_folder-0.2.0.dist-info/WHEEL
tmp_folder-0.2.0.dist-info/METADATA
tmp_folder-0.2.0.dist-info/RECORD
