Metadata-Version: 2.1
Name: tmp-folder
Version: 0.2.0
Summary: Extends python `TemporaryDirectory` and make it even easier to use, as a decorator.
Home-page: https://jalvaradosegura.github.io/tmp-folder/
License: MIT
Author: Jorge Alvarado
Author-email: alvaradosegurajorge@gmail.com
Requires-Python: >=3.7,<4.0
Classifier: License :: OSI Approved :: MIT License
Classifier: Programming Language :: Python :: 3
Classifier: Programming Language :: Python :: 3.7
Classifier: Programming Language :: Python :: 3.8
Classifier: Programming Language :: Python :: 3.9
Classifier: Programming Language :: Python :: 3.10
Classifier: Programming Language :: Python :: 3.11
Requires-Dist: typing-extensions (>=4.0.1,<5.0.0)
Project-URL: Repository, https://github.com/jalvaradosegura/tmp-folder
